QAOAKit/__init__.py
QAOAKit/build_tables.py
QAOAKit/examples_utils.py
QAOAKit/parameter_optimization.py
QAOAKit/qaoa.py
QAOAKit/qiskit_interface.py
QAOAKit/utils.py
QAOAKit-0.1.13.dist-info/LICENSE
QAOAKit-0.1.13.dist-info/METADATA
QAOAKit-0.1.13.dist-info/WHEEL
QAOAKit-0.1.13.dist-info/top_level.txt
QAOAKit-0.1.13.dist-info/zip-safe
QAOAKit-0.1.13.dist-info/RECORD
