Metadata-Version: 2.1
Name: QAOAKit
Version: 0.1.13
Summary: A Toolkit for Reproducible Study, Application and Verification of QAOA
Home-page: https://github.com/QAOAKit/QAOAKit
Author: Ruslan Shaydulin
Author-email: ruslan@shaydul.in
License: UNKNOWN
Platform: UNKNOWN
Requires-Python: >=3, <4
License-File: LICENSE
Requires-Dist: qiskit (==0.29.0)
Requires-Dist: pynauty (==1.0.0)
Requires-Dist: qiskit-optimization
Requires-Dist: pandas
Requires-Dist: networkx
Requires-Dist: numpy
Requires-Dist: pytest
Requires-Dist: tqdm
Requires-Dist: cvxgraphalgs
Requires-Dist: cvxopt
Requires-Dist: scikit-learn (==1.0)
Requires-Dist: notebook
Requires-Dist: matplotlib
Requires-Dist: seaborn
